utradeconnect/__init__.py
utradeconnect/__version__.py
utradeconnect/apiConfig.py
utradeconnect/base.py
utradeconnect/config.ini
utradeconnect/exception.py
utradeconnect/index.py
utradeconnect/market.py
utradeconnect/marketSocket.py
utradeconnect/orderSocket.py
utradeconnect/orders.py
utradeconnect/request.py
utradeconnect-1.0.4.dist-info/licenses/LICENSE
utradeconnect-1.0.4.dist-info/METADATA
utradeconnect-1.0.4.dist-info/WHEEL
utradeconnect-1.0.4.dist-info/top_level.txt
utradeconnect-1.0.4.dist-info/RECORD
